octodns_desec/__init__.py
octodns_desec-1.3.0.dist-info/licenses/LICENSE
octodns_desec-1.3.0.dist-info/METADATA
octodns_desec-1.3.0.dist-info/WHEEL
octodns_desec-1.3.0.dist-info/top_level.txt
octodns_desec-1.3.0.dist-info/RECORD
