Metadata-Version: 2.4
Name: octodns-desec
Version: 1.3.0
Summary:  deSEC.io provider for octoDNS
Home-page: https://github.com/rootshell-labs/octodns-desec
Author: TilCreator and blackdotraven
Author-email: contact.octodns@tc-j.de
License: MIT
Requires-Python: >=3.10
License-File: LICENSE
Requires-Dist: octodns>=1.0.0
Requires-Dist: requests>=2.32.3
Provides-Extra: dev
Requires-Dist: pytest; extra == "dev"
Requires-Dist: pytest-cov; extra == "dev"
Requires-Dist: pytest-network; extra == "dev"
Requires-Dist: black<25.0.0,>=24.3.0; extra == "dev"
Requires-Dist: build>=0.7.0; extra == "dev"
Requires-Dist: docutils<=0.20.1; extra == "dev"
Requires-Dist: isort>=5.11.5; extra == "dev"
Requires-Dist: pyflakes>=2.2.0; extra == "dev"
Requires-Dist: readme_renderer[md]>=26.0; extra == "dev"
Requires-Dist: twine>=3.4.2; extra == "dev"
Provides-Extra: test
Requires-Dist: pytest; extra == "test"
Requires-Dist: pytest-cov; extra == "test"
Requires-Dist: pytest-network; extra == "test"
Dynamic: author
Dynamic: author-email
Dynamic: description
Dynamic: description-content-type
Dynamic: home-page
Dynamic: license
Dynamic: license-file
Dynamic: provides-extra
Dynamic: requires-dist
Dynamic: requires-python
Dynamic: summary
